pyconfig_extension/__init__.py
pyconfig_extension/guard.py
pyconfig_extension/abstracts/__init__.py
pyconfig_extension/abstracts/configuration_extensions.py
pyconfig_extension/abstracts/configuration_path.py
pyconfig_extension/abstracts/iconfiguration.py
pyconfig_extension/abstracts/iconfiguration_builder.py
pyconfig_extension/abstracts/iconfiguration_provider.py
pyconfig_extension/abstracts/iconfiguration_root.py
pyconfig_extension/abstracts/stream_configuration_provider.py
pyconfig_extension/abstracts/stream_configuration_source.py
pyconfig_extension/abstracts/binder/__init__.py
pyconfig_extension/abstracts/binder/binder_option_listener.py
pyconfig_extension/abstracts/binder/binder_options.py
pyconfig_extension/abstracts/binder/binder_utils.py
pyconfig_extension/abstracts/binder/binding_point.py
pyconfig_extension/command_line/__init__.py
pyconfig_extension/command_line/extensions.py
pyconfig_extension/command_line/provider.py
pyconfig_extension/command_line/source.py
pyconfig_extension/core/__init__.py
pyconfig_extension/core/_internal_configuration_root_extensions.py
pyconfig_extension/core/chained_configuration_provider.py
pyconfig_extension/core/chained_configuration_source.py
pyconfig_extension/core/configuration_builder.py
pyconfig_extension/core/configuration_key_comparer.py
pyconfig_extension/core/configuration_provider.py
pyconfig_extension/core/configuration_root.py
pyconfig_extension/core/configuration_section.py
pyconfig_extension/core/extensions.py
pyconfig_extension/core/memory_configuration_provider.py
pyconfig_extension/core/memory_configuration_source.py
pyconfig_extension/core/ordinal_ignore_case_dict.py
pyconfig_extension/environment_variables/__init__.py
pyconfig_extension/environment_variables/extensions.py
pyconfig_extension/environment_variables/provider.py
pyconfig_extension/environment_variables/source.py
pyconfig_extension/file/__init__.py
pyconfig_extension/file/file_configuration_provider.py
pyconfig_extension-0.0.1.dist-info/LICENSE
pyconfig_extension-0.0.1.dist-info/METADATA
pyconfig_extension-0.0.1.dist-info/WHEEL
pyconfig_extension-0.0.1.dist-info/top_level.txt
pyconfig_extension-0.0.1.dist-info/RECORD
