Metadata-Version: 2.1
Name: pyconfig-extension
Version: 0.0.1
Summary: configuration manager for python
Author: Reza Sadeghi
Author-email: rezasadeghikhas@gmail.com
License: Apache2
Classifier: Development Status :: 3 - Alpha
Classifier: Intended Audience :: Developers
Classifier: Topic :: System :: Logging
Classifier: Topic :: Software Development :: Libraries
Classifier: Topic :: Internet :: Log Analysis
Classifier: License :: OSI Approved :: Apache Software License
Classifier: Programming Language :: Python :: 3.11
License-File: LICENSE
Requires-Dist: json5 (==0.9.11)
Requires-Dist: multipledispatch (==0.6.0)
